trajnetplusplustools/__init__.py
trajnetplusplustools/data.py
trajnetplusplustools/dataset.py
trajnetplusplustools/dataset_stats.py
trajnetplusplustools/interactions.py
trajnetplusplustools/kalman.py
trajnetplusplustools/metrics.py
trajnetplusplustools/reader.py
trajnetplusplustools/show.py
trajnetplusplustools/summarize.py
trajnetplusplustools/summarize_new.py
trajnetplusplustools/trajectories.py
trajnetplusplustools/visualize_type.py
trajnetplusplustools/writers.py
trajnetplusplustools-0.3.0.dist-info/LICENSE
trajnetplusplustools-0.3.0.dist-info/METADATA
trajnetplusplustools-0.3.0.dist-info/WHEEL
trajnetplusplustools-0.3.0.dist-info/top_level.txt
trajnetplusplustools-0.3.0.dist-info/RECORD
