Metadata-Version: 2.1
Name: trajnetplusplustools
Version: 0.3.0
Summary: Trajnet++ tools.
Home-page: https://github.com/vita-epfl/trajnetplusplustools
Author: Parth Kothari
Author-email: parth.kothari@epfl.ch
License: MIT
Platform: UNKNOWN
Classifier: Development Status :: 4 - Beta
Classifier: Intended Audience :: Developers
Classifier: Natural Language :: English
Classifier: License :: OSI Approved :: MIT License
Classifier: Operating System :: OS Independent
Classifier: Programming Language :: Python
Classifier: Programming Language :: Python :: 2.7
Classifier: Programming Language :: Python :: 3.4
Classifier: Programming Language :: Python :: 3.5
Classifier: Programming Language :: Python :: 3.6
Classifier: Programming Language :: Python :: Implementation :: PyPy
Requires-Dist: numpy
Requires-Dist: scipy
Requires-Dist: pykalman
Provides-Extra: plot
Requires-Dist: matplotlib ; extra == 'plot'
Provides-Extra: test
Requires-Dist: pylint ; extra == 'test'
Requires-Dist: pytest ; extra == 'test'
